beeline-stubs/__init__.pyi
beeline-stubs/propagation/__init__.pyi
beeline-stubs/propagation/honeycomb.pyi
beeline-stubs/trace.pyi
beeline-stubs/version.pyi
libhoney-stubs/__init__.pyi
libhoney-stubs/client.pyi
libhoney-stubs/event.pyi
libhoney-stubs/transmission.pyi
honeycomb_stubs-0.2.2.dist-info/WHEEL
honeycomb_stubs-0.2.2.dist-info/METADATA
honeycomb_stubs-0.2.2.dist-info/RECORD
