Metadata-Version: 2.1
Name: honeycomb-stubs
Version: 0.2.2
Summary: Type stubs for the libhoney and beeline packages
Home-page: https://github.com/benesch/honeycomb-stubs
License: Apache-2.0
Author: Nikhil Benesch
Author-email: nikhil.benesch@gmail.com
Requires-Python: >=3.9,<4.0
Classifier: License :: OSI Approved :: Apache Software License
Classifier: Programming Language :: Python :: 3
Classifier: Programming Language :: Python :: 3.10
Classifier: Programming Language :: Python :: 3.9
Requires-Dist: honeycomb-beeline (>=3.0.0,<4.0.0)
Requires-Dist: libhoney (>=2.0.0,<3.0.0)
Project-URL: Repository, https://github.com/benesch/honeycomb-stubs
